dvatioff_audio/__init__.py
dvatioff_audio/general_utils.py
dvatioff_audio/globals.py
dvatioff_audio/gui_css.py
dvatioff_audio/gui_utils.py
dvatioff_audio/utils.py
dvatioff_audio/waapi_utils.py
dvatioff_audio/examples/__init__.py
dvatioff_audio/examples/build.py
dvatioff_audio/examples/main.py
dvatioff_audio/examples/main_window_framework.py
dvatioff_audio/examples/notification_window_framework.py
dvatioff_audio/examples/text_speech_verify_window_framework.py
dvatioff_audio/gui/__init__.py
dvatioff_audio/gui/gui_css.py
dvatioff_audio/gui/gui_utils.py
dvatioff_audio/voice/__init__.py
dvatioff_audio/voice/azure_speech2text.py
dvatioff_audio/voice/azure_text2speech.py
dvatioff_audio/voice/voice_utils.py
dvatioff_audio/waapi/__init__.py
dvatioff_audio/waapi/waapi_connector.py
dvatioff_audio/waapi/waapi_object_selector.py
dvatioff_audio/waapi/waapi_profiler_log_capturer.py
dvatioff_audio/waapi/waapi_utils.py
dvatioff_audio-0.3.6.dist-info/METADATA
dvatioff_audio-0.3.6.dist-info/WHEEL
dvatioff_audio-0.3.6.dist-info/top_level.txt
dvatioff_audio-0.3.6.dist-info/RECORD
