Metadata-Version: 2.1
Name: dvatioff-audio
Version: 0.3.6
Summary: Personal audio utils package
Home-page: https://github.com/dvatiOFF/python-audio-utils
Author: dvatiOFF
Author-email: dvatioff@gmail.com
Classifier: Programming Language :: Python :: 3
Classifier: Operating System :: OS Independent
Requires-Python: >=3.10
